cr_package_installable/__init__.py
cr_package_installable/utils.py
cr_package_installable/length/__init__.py
cr_package_installable/length/api.py
cr_package_installable/length/core.py
cr_package_installable/weight/__init__.py
cr_package_installable/weight/api.py
cr_package_installable/weight/core.py
cr_package_installable-0.1.4.dist-info/licenses/LICENSE
cr_package_installable-0.1.4.dist-info/METADATA
cr_package_installable-0.1.4.dist-info/WHEEL
cr_package_installable-0.1.4.dist-info/top_level.txt
cr_package_installable-0.1.4.dist-info/RECORD
