Metadata-Version: 2.4
Name: cr_package_installable
Version: 0.1.4
Summary: A package for converting impyrial lengths and weights.
Author: Josue Afouda
License-File: LICENSE
Requires-Dist: numpy>=1.10
Requires-Dist: pandas
Dynamic: author
Dynamic: description
Dynamic: description-content-type
Dynamic: license-file
Dynamic: requires-dist
Dynamic: summary
